scrapy_selenium/__init__.py
scrapy_selenium/http.py
scrapy_selenium/middlewares.py
tests/__init__.py
tests/test_cases.py
tests/test_middlewares.py
py_selenium_scrapy-0.0.8.dist-info/LICENCE
py_selenium_scrapy-0.0.8.dist-info/METADATA
py_selenium_scrapy-0.0.8.dist-info/WHEEL
py_selenium_scrapy-0.0.8.dist-info/top_level.txt
py_selenium_scrapy-0.0.8.dist-info/RECORD
