Metadata-Version: 2.1
Name: py-selenium-scrapy
Version: 0.0.8
Summary: Scrapy with selenium in Python
Home-page: https://github.com/sushil-bigfuture/scrapy-selenium
Author: Sushil
Author-email: sushil@bigfuture.com.au
License: UNKNOWN
Platform: UNKNOWN
Classifier: Programming Language :: Python :: 3
Classifier: License :: OSI Approved :: MIT License
Classifier: Operating System :: OS Independent
Requires-Python: >=3.6
Requires-Dist: scrapy
Requires-Dist: selenium
